trino_mcp/__init__.py
trino_mcp/__main__.py
trino_mcp/client.py
trino_mcp/config.py
trino_mcp/server.py
trino_mcp-0.1.3.dist-info/METADATA
trino_mcp-0.1.3.dist-info/WHEEL
trino_mcp-0.1.3.dist-info/entry_points.txt
trino_mcp-0.1.3.dist-info/licenses/LICENSE
trino_mcp-0.1.3.dist-info/RECORD
