Metadata-Version: 2.4
Name: trino-mcp
Version: 0.1.3
Summary: A simple Model Context Protocol (MCP) server for Trino with OAuth support
Project-URL: Homepage, https://github.com/weijie-tan3/trino-mcp
Project-URL: Repository, https://github.com/weijie-tan3/trino-mcp
Project-URL: Issues, https://github.com/weijie-tan3/trino-mcp/issues
Project-URL: Documentation, https://github.com/weijie-tan3/trino-mcp#readme
Author: Trino MCP Contributors
License: MIT
License-File: LICENSE
Keywords: ai,llm,mcp,model-context-protocol,trino
Classifier: Development Status :: 3 - Alpha
Classifier: Intended Audience :: Developers
Classifier: License :: OSI Approved :: MIT License
Classifier: Programming Language :: Python :: 3
Classifier: Programming Language :: Python :: 3.10
Classifier: Programming Language :: Python :: 3.11
Classifier: Programming Language :: Python :: 3.12
Classifier: Topic :: Database
Classifier: Topic :: Software Development :: Libraries :: Python Modules
Requires-Python: >=3.10
Requires-Dist: mcp>=1.6.0
Requires-Dist: python-dotenv>=1.0.0
Requires-Dist: sqlglot>=27.0.0
Requires-Dist: trino>=0.333.0
